bjones_testing_actions/__init__.py
bjones_testing_actions-0.3.37.dist-info/METADATA
bjones_testing_actions-0.3.37.dist-info/WHEEL
bjones_testing_actions-0.3.37.dist-info/top_level.txt
bjones_testing_actions-0.3.37.dist-info/RECORD
