Metadata-Version: 2.4
Name: bjones-testing-actions
Version: 0.3.37
Summary: Simple test
Project-URL: Homepage, https://github.com/heroku/testing_actions
Project-URL: Documentation, https://github.com/heroku/testing_actions
Project-URL: Repository, https://github.com/heroku/testing_actions.git
Project-URL: Bug Tracker, https://github.com/heroku/testing_actions/issues
Project-URL: Changelog, https://github.com/heroku/testing_actions/CHANGELOG.md
Requires-Python: >=3.10
Requires-Dist: aiohttp>=3.11.12
Requires-Dist: orjson>=3.10.15
Provides-Extra: test
Requires-Dist: pytest>=7.0.0; extra == "test"
Requires-Dist: pytest-asyncio>=0.21.0; extra == "test"
Requires-Dist: pytest-cov>=4.0.0; extra == "test"
Requires-Dist: pytest-mock>=3.10.0; extra == "test"
Requires-Dist: ruff>=0.1.0; extra == "test"
Requires-Dist: coverage>=7.0.0; extra == "test"
